new_pymigration/Auros.py
new_pymigration/__init__.py
new_pymigration/cleasing.py
new_pymigration/pyConverterUI.py
new_pymigration/pymigration.py
new_pymigration/setup.py
new_pymigration-0.1.dist-info/METADATA
new_pymigration-0.1.dist-info/WHEEL
new_pymigration-0.1.dist-info/top_level.txt
new_pymigration-0.1.dist-info/RECORD
